{
  "py:attr": {
    "ax": [
      "lib/mpl_toolkits/axes_grid1/colorbar.py:docstring of mpl_toolkits.axes_grid1.colorbar.ColorbarBase:23"
    ],
    "axis": [
      "lib/matplotlib/category.py:docstring of matplotlib.category.StrCategoryLocator.tick_values:5",
      "lib/matplotlib/dates.py:docstring of matplotlib.dates.AutoDateLocator.tick_values:5",
      "lib/matplotlib/dates.py:docstring of matplotlib.dates.MicrosecondLocator.tick_values:5",
      "lib/matplotlib/dates.py:docstring of matplotlib.dates.RRuleLocator.tick_values:5",
      "lib/matplotlib/dates.py:docstring of matplotlib.dates.YearLocator.tick_values:5",
      "lib/matplotlib/ticker.py:docstring of matplotlib.ticker.AutoMinorLocator.tick_values:5",
      "lib/matplotlib/ticker.py:docstring of matplotlib.ticker.IndexLocator.tick_values:5",
      "lib/matplotlib/ticker.py:docstring of matplotlib.ticker.LinearLocator.tick_values:5",
      "lib/matplotlib/ticker.py:docstring of matplotlib.ticker.Locator.tick_values:5",
      "lib/matplotlib/ticker.py:docstring of matplotlib.ticker.LogLocator.tick_values:5",
      "lib/matplotlib/ticker.py:docstring of matplotlib.ticker.LogitLocator.tick_values:5",
      "lib/matplotlib/ticker.py:docstring of matplotlib.ticker.MaxNLocator.tick_values:5",
      "lib/matplotlib/ticker.py:docstring of matplotlib.ticker.MultipleLocator.tick_values:5",
      "lib/matplotlib/ticker.py:docstring of matplotlib.ticker.OldAutoLocator.tick_values:5",
      "lib/matplotlib/ticker.py:docstring of matplotlib.ticker.SymmetricalLogLocator.tick_values:5"
    ],
    "button": [
      "doc/users/prev_whats_new/whats_new_3.1.0.rst:338"
    ],
    "cbar_axes": [
      "lib/mpl_toolkits/axes_grid1/axes_grid.py:docstring of mpl_toolkits.axes_grid1.axes_grid.ImageGrid:49",
      "lib/mpl_toolkits/axisartist/axes_grid.py:docstring of mpl_toolkits.axisartist.axes_grid.ImageGrid:49"
    ],
    "dividers": [
      "lib/mpl_toolkits/axes_grid1/colorbar.py:docstring of mpl_toolkits.axes_grid1.colorbar.ColorbarBase:29"
    ],
    "eventson": [
      "lib/matplotlib/widgets.py:docstring of matplotlib.widgets.CheckButtons.set_active:4",
      "lib/matplotlib/widgets.py:docstring of matplotlib.widgets.RadioButtons.set_active:4"
    ],
    "fmt_zdata": [
      "lib/mpl_toolkits/mplot3d/axes3d.py:docstring of mpl_toolkits.mplot3d.axes3d.Axes3D.format_zdata:2"
    ],
    "height": [
      "lib/matplotlib/transforms.py:docstring of matplotlib.transforms.Bbox.bounds:2"
    ],
    "input_dims": [
      "lib/matplotlib/transforms.py:docstring of matplotlib.transforms.AffineBase.transform:14",
      "lib/matplotlib/transforms.py:docstring of matplotlib.transforms.AffineBase.transform:8",
      "lib/matplotlib/transforms.py:docstring of matplotlib.transforms.AffineBase.transform_affine:15",
      "lib/matplotlib/transforms.py:docstring of matplotlib.transforms.AffineBase.transform_affine:21",
      "lib/matplotlib/transforms.py:docstring of matplotlib.transforms.AffineBase.transform_non_affine:14",
      "lib/matplotlib/transforms.py:docstring of matplotlib.transforms.AffineBase.transform_non_affine:20",
      "lib/matplotlib/transforms.py:docstring of matplotlib.transforms.CompositeGenericTransform.transform_affine:15",
      "lib/matplotlib/transforms.py:docstring of matplotlib.transforms.CompositeGenericTransform.transform_affine:21",
      "lib/matplotlib/transforms.py:docstring of matplotlib.transforms.CompositeGenericTransform.transform_non_affine:14",
      "lib/matplotlib/transforms.py:docstring of matplotlib.transforms.CompositeGenericTransform.transform_non_affine:20",
      "lib/matplotlib/transforms.py:docstring of matplotlib.transforms.IdentityTransform.transform:14",
      "lib/matplotlib/transforms.py:docstring of matplotlib.transforms.IdentityTransform.transform:8",
      "lib/matplotlib/transforms.py:docstring of matplotlib.transforms.IdentityTransform.transform_affine:15",
      "lib/matplotlib/transforms.py:docstring of matplotlib.transforms.IdentityTransform.transform_affine:21",
      "lib/matplotlib/transforms.py:docstring of matplotlib.transforms.IdentityTransform.transform_non_affine:14",
      "lib/matplotlib/transforms.py:docstring of matplotlib.transforms.IdentityTransform.transform_non_affine:20"
    ],
    "lines": [
      "lib/matplotlib/colorbar.py:docstring of matplotlib.colorbar.ColorbarBase.add_lines:4",
      "lib/mpl_toolkits/axes_grid1/colorbar.py:docstring of mpl_toolkits.axes_grid1.colorbar.ColorbarBase:26"
    ],
    "matplotlib.axes.Axes.dataLim": [
      "doc/api/prev_api_changes/api_changes_0.99.x.rst:23"
    ],
    "matplotlib.axes.Axes.frame": [
      "doc/api/prev_api_changes/api_changes_0.98.x.rst:89"
    ],
    "matplotlib.axes.Axes.lines": [
      "doc/tutorials/intermediate/artists.rst:408",
      "doc/tutorials/intermediate/artists.rst:92"
    ],
    "matplotlib.axes.Axes.patch": [
      "doc/api/prev_api_changes/api_changes_0.98.x.rst:89",
      "doc/tutorials/intermediate/artists.rst:174",
      "doc/tutorials/intermediate/artists.rst:392"
    ],
    "matplotlib.axes.Axes.patches": [
      "doc/tutorials/intermediate/artists.rst:431"
    ],
    "matplotlib.axes.Axes.transAxes": [
      "lib/mpl_toolkits/axes_grid1/anchored_artists.py:docstring of mpl_toolkits.axes_grid1.anchored_artists.AnchoredDirectionArrows:8"
    ],
    "matplotlib.axes.Axes.transData": [
      "lib/mpl_toolkits/axes_grid1/anchored_artists.py:docstring of mpl_toolkits.axes_grid1.anchored_artists.AnchoredAuxTransformBox:11",
      "lib/mpl_toolkits/axes_grid1/anchored_artists.py:docstring of mpl_toolkits.axes_grid1.anchored_artists.AnchoredEllipse:8",
      "lib/mpl_toolkits/axes_grid1/anchored_artists.py:docstring of mpl_toolkits.axes_grid1.anchored_artists.AnchoredSizeBar:8"
    ],
    "matplotlib.axes.Axes.viewLim": [
      "doc/api/prev_api_changes/api_changes_0.99.x.rst:23"
    ],
    "matplotlib.axes.Axes.xaxis": [
      "doc/tutorials/intermediate/artists.rst:530"
    ],
    "matplotlib.axes.Axes.yaxis": [
      "doc/tutorials/intermediate/artists.rst:530"
    ],
    "matplotlib.axis.Axis.label": [
      "doc/tutorials/intermediate/artists.rst:577"
    ],
    "matplotlib.cm.ScalarMappable.callbacksSM": [
      "doc/api/prev_api_changes/api_changes_0.98.0.rst:10"
    ],
    "matplotlib.colorbar.ColorbarBase.ax": [
      "doc/api/prev_api_changes/api_changes_1.3.x.rst:100"
    ],
    "matplotlib.colors.Colormap.name": [
      "lib/matplotlib/cm.py:docstring of matplotlib.cm.register_cmap:10"
    ],
    "matplotlib.figure.Figure.patch": [
      "doc/api/prev_api_changes/api_changes_0.98.x.rst:89",
      "doc/tutorials/intermediate/artists.rst:174",
      "doc/tutorials/intermediate/artists.rst:289"
    ],
    "matplotlib.figure.Figure.transFigure": [
      "doc/tutorials/intermediate/artists.rst:339"
    ],
    "max": [
      "lib/matplotlib/transforms.py:docstring of matplotlib.transforms.Bbox.p1:4"
    ],
    "min": [
      "lib/matplotlib/transforms.py:docstring of matplotlib.transforms.Bbox.p0:4"
    ],
    "mpl_toolkits.mplot3d.axis3d._axinfo": [
      "doc/api/toolkits/mplot3d.rst:40"
    ],
    "name": [
      "lib/matplotlib/scale.py:docstring of matplotlib.scale.ScaleBase:8"
    ],
    "output_dims": [
      "lib/matplotlib/transforms.py:docstring of matplotlib.transforms.AffineBase.transform:14",
      "lib/matplotlib/transforms.py:docstring of matplotlib.transforms.AffineBase.transform_affine:21",
      "lib/matplotlib/transforms.py:docstring of matplotlib.transforms.AffineBase.transform_non_affine:20",
      "lib/matplotlib/transforms.py:docstring of matplotlib.transforms.CompositeGenericTransform.transform_affine:21",
      "lib/matplotlib/transforms.py:docstring of matplotlib.transforms.CompositeGenericTransform.transform_non_affine:20",
      "lib/matplotlib/transforms.py:docstring of matplotlib.transforms.IdentityTransform.transform:14",
      "lib/matplotlib/transforms.py:docstring of matplotlib.transforms.IdentityTransform.transform_affine:21",
      "lib/matplotlib/transforms.py:docstring of matplotlib.transforms.IdentityTransform.transform_non_affine:20"
    ],
    "triangulation": [
      "lib/matplotlib/tri/trirefine.py:docstring of matplotlib.tri.UniformTriRefiner.refine_triangulation:2"
    ],
    "use_sticky_edges": [
      "lib/matplotlib/pyplot.py:docstring of matplotlib.pyplot.margins:53"
    ],
    "width": [
      "lib/matplotlib/transforms.py:docstring of matplotlib.transforms.Bbox.bounds:2"
    ],
    "xmax": [
      "lib/matplotlib/transforms.py:docstring of matplotlib.transforms.Bbox.x1:4"
    ],
    "xmin": [
      "lib/matplotlib/transforms.py:docstring of matplotlib.transforms.Bbox.x0:4"
    ],
    "ymax": [
      "lib/matplotlib/transforms.py:docstring of matplotlib.transforms.Bbox.y1:4"
    ],
    "ymin": [
      "lib/matplotlib/transforms.py:docstring of matplotlib.transforms.Bbox.y0:4"
    ]
  },
  "py:class": {
    "Cursors": [
      "lib/matplotlib/backend_bases.py:docstring of matplotlib.backend_bases.NavigationToolbar2.set_cursor:2"
    ],
    "FigureCanvasQTAgg": [
      "doc/api/prev_api_changes/api_changes_2.2.0.rst:215"
    ],
    "Patch3DCollection": [
      "doc/api/toolkits/mplot3d.rst:83:<autosummary>:1"
    ],
    "Path3DCollection": [
      "doc/api/toolkits/mplot3d.rst:83:<autosummary>:1"
    ],
    "_FancyAxislineStyle.FilledArrow": [
      "<unknown>:1"
    ],
    "_FancyAxislineStyle.SimpleArrow": [
      "<unknown>:1"
    ],
    "backend_qt5.FigureCanvasQT": [
      "doc/api/prev_api_changes/api_changes_2.2.0.rst:199"
    ],
    "backend_qt5.FigureCanvasQTAgg": [
      "doc/api/prev_api_changes/api_changes_2.2.0.rst:210"
    ],
    "datetime": [
      "lib/matplotlib/dates.py:docstring of matplotlib.dates.mx2num:2"
    ],
    "dateutil.rrule.rrulebase": [
      "<external>/rrule.py:docstring of matplotlib.dates.rrule:1"
    ],
    "dviread.PsfontsMap": [
      "lib/matplotlib/dviread.py:docstring of matplotlib.dviread.DviFont:20"
    ],
    "matplotlib.axes.Subplot": [
      "doc/tutorials/intermediate/artists.rst:36",
      "doc/tutorials/intermediate/artists.rst:59"
    ],
    "matplotlib.axes._axes.Axes": [
      "doc/api/artist_api.rst:189",
      "doc/api/axes_api.rst:616",
      "lib/matplotlib/projections/polar.py:docstring of matplotlib.projections.polar.PolarAxes:1",
      "lib/mpl_toolkits/axes_grid1/mpl_axes.py:docstring of mpl_toolkits.axes_grid1.mpl_axes.Axes:1",
      "lib/mpl_toolkits/axisartist/axislines.py:docstring of mpl_toolkits.axisartist.axislines.Axes:1",
      "lib/mpl_toolkits/mplot3d/axes3d.py:docstring of mpl_toolkits.mplot3d.axes3d.Axes3D:1"
    ],
    "matplotlib.axes._base._AxesBase": [
      "doc/api/artist_api.rst:189",
      "doc/api/axes_api.rst:616",
      "lib/matplotlib/axes/_axes.py:docstring of matplotlib.axes.Axes:1"
    ],
    "matplotlib.backend_bases.FigureCanvas": [
      "doc/tutorials/intermediate/artists.rst:20",
      "doc/tutorials/intermediate/artists.rst:22",
      "doc/tutorials/intermediate/artists.rst:28"
    ],
    "matplotlib.backend_bases.Renderer": [
      "doc/tutorials/intermediate/artists.rst:22",
      "doc/tutorials/intermediate/artists.rst:28"
    ],
    "matplotlib.backend_bases._Backend": [
      "lib/matplotlib/backend_bases.py:docstring of matplotlib.backend_bases.ShowBase:1"
    ],
    "matplotlib.backend_tools._ToolEnableAllNavigation": [
      "lib/matplotlib/backend_tools.py:docstring of matplotlib.backend_tools.ToolEnableAllNavigation:1"
    ],
    "matplotlib.backend_tools._ToolEnableNavigation": [
      "lib/matplotlib/backend_tools.py:docstring of matplotlib.backend_tools.ToolEnableNavigation:1"
    ],
    "matplotlib.backends._backend_pdf_ps.RendererPDFPSBase": [
      "lib/matplotlib/backends/backend_pdf.py:docstring of matplotlib.backends.backend_pdf.RendererPdf:1",
      "lib/matplotlib/backends/backend_ps.py:docstring of matplotlib.backends.backend_ps.RendererPS:1"
    ],
    "matplotlib.backends._backend_tk.FigureCanvasTk": [
      "lib/matplotlib/backends/backend_tkagg.py:docstring of matplotlib.backends.backend_tkagg.FigureCanvasTkAgg:1"
    ],
    "matplotlib.backends.backend_webagg_core.FigureCanvasWebAggCore": [
      "lib/matplotlib/backends/backend_nbagg.py:docstring of matplotlib.backends.backend_nbagg.FigureCanvasNbAgg:1"
    ],
    "matplotlib.backends.backend_webagg_core.FigureManagerWebAgg": [
      "lib/matplotlib/backends/backend_nbagg.py:docstring of matplotlib.backends.backend_nbagg.FigureManagerNbAgg:1"
    ],
    "matplotlib.backends.backend_webagg_core.NavigationToolbar2WebAgg": [
      "lib/matplotlib/backends/backend_nbagg.py:docstring of matplotlib.backends.backend_nbagg.NavigationIPy:1"
    ],
    "matplotlib.cm.Wistia": [
      "doc/users/prev_whats_new/whats_new_1.4.rst:21"
    ],
    "matplotlib.collections._CollectionWithSizes": [
      "doc/api/artist_api.rst:189",
      "doc/api/collections_api.rst:13",
      "lib/matplotlib/collections.py:docstring of matplotlib.collections.CircleCollection:1",
      "lib/matplotlib/collections.py:docstring of matplotlib.collections.PathCollection:1",
      "lib/matplotlib/collections.py:docstring of matplotlib.collections.PolyCollection:1",
      "lib/matplotlib/collections.py:docstring of matplotlib.collections.RegularPolyCollection:1"
    ],
    "matplotlib.contours.ContourSet": [
      "lib/mpl_toolkits/axes_grid1/colorbar.py:docstring of mpl_toolkits.axes_grid1.colorbar.colorbar:92"
    ],
    "matplotlib.dates.rrulewrapper": [
      "doc/api/dates_api.rst:11"
    ],
    "matplotlib.figure._AxesStack": [
      "lib/matplotlib/figure.py:docstring of matplotlib.figure.AxesStack:1"
    ],
    "matplotlib.font_manager._JSONEncoder": [
      "lib/matplotlib/font_manager.py:docstring of matplotlib.font_manager.JSONEncoder:1"
    ],
    "matplotlib.image.Image": [
      "lib/mpl_toolkits/axes_grid1/colorbar.py:docstring of mpl_toolkits.axes_grid1.colorbar.colorbar:20"
    ],
    "matplotlib.image._ImageBase": [
      "doc/api/artist_api.rst:189",
      "lib/matplotlib/image.py:docstring of matplotlib.image.AxesImage:1",
      "lib/matplotlib/image.py:docstring of matplotlib.image.BboxImage:1",
      "lib/matplotlib/image.py:docstring of matplotlib.image.FigureImage:1"
    ],
    "matplotlib.patches.ArrowStyle._Base": [
      "lib/matplotlib/patches.py:docstring of matplotlib.patches.ArrowStyle.Fancy:1",
      "lib/matplotlib/patches.py:docstring of matplotlib.patches.ArrowStyle.Simple:1",
      "lib/matplotlib/patches.py:docstring of matplotlib.patches.ArrowStyle.Wedge:1"
    ],
    "matplotlib.patches.ArrowStyle._Bracket": [
      "lib/matplotlib/patches.py:docstring of matplotlib.patches.ArrowStyle.BarAB:1",
      "lib/matplotlib/patches.py:docstring of matplotlib.patches.ArrowStyle.BracketA:1",
      "lib/matplotlib/patches.py:docstring of matplotlib.patches.ArrowStyle.BracketAB:1",
      "lib/matplotlib/patches.py:docstring of matplotlib.patches.ArrowStyle.BracketB:1"
    ],
    "matplotlib.patches.ArrowStyle._Curve": [
      "lib/matplotlib/patches.py:docstring of matplotlib.patches.ArrowStyle.Curve:1",
      "lib/matplotlib/patches.py:docstring of matplotlib.patches.ArrowStyle.CurveA:1",
      "lib/matplotlib/patches.py:docstring of matplotlib.patches.ArrowStyle.CurveAB:1",
      "lib/matplotlib/patches.py:docstring of matplotlib.patches.ArrowStyle.CurveB:1",
      "lib/matplotlib/patches.py:docstring of matplotlib.patches.ArrowStyle.CurveFilledA:1",
      "lib/matplotlib/patches.py:docstring of matplotlib.patches.ArrowStyle.CurveFilledAB:1",
      "lib/matplotlib/patches.py:docstring of matplotlib.patches.ArrowStyle.CurveFilledB:1"
    ],
    "matplotlib.patches.BoxStyle._Base": [
      "lib/matplotlib/patches.py:docstring of matplotlib.patches.BoxStyle.Circle:1",
      "lib/matplotlib/patches.py:docstring of matplotlib.patches.BoxStyle.DArrow:1",
      "lib/matplotlib/patches.py:docstring of matplotlib.patches.BoxStyle.LArrow:1",
      "lib/matplotlib/patches.py:docstring of matplotlib.patches.BoxStyle.Round4:1",
      "lib/matplotlib/patches.py:docstring of matplotlib.patches.BoxStyle.Round:1",
      "lib/matplotlib/patches.py:docstring of matplotlib.patches.BoxStyle.Sawtooth:1",
      "lib/matplotlib/patches.py:docstring of matplotlib.patches.BoxStyle.Square:1"
    ],
    "matplotlib.patches.ConnectionStyle._Base": [
      "lib/matplotlib/patches.py:docstring of matplotlib.patches.ConnectionStyle.Angle3:1",
      "lib/matplotlib/patches.py:docstring of matplotlib.patches.ConnectionStyle.Angle:1",
      "lib/matplotlib/patches.py:docstring of matplotlib.patches.ConnectionStyle.Arc3:1",
      "lib/matplotlib/patches.py:docstring of matplotlib.patches.ConnectionStyle.Arc:1",
      "lib/matplotlib/patches.py:docstring of matplotlib.patches.ConnectionStyle.Bar:1"
    ],
    "matplotlib.patches._Style": [
      "lib/matplotlib/patches.py:docstring of matplotlib.patches.ArrowStyle:1",
      "lib/matplotlib/patches.py:docstring of matplotlib.patches.BoxStyle:1",
      "lib/matplotlib/patches.py:docstring of matplotlib.patches.ConnectionStyle:1",
      "lib/mpl_toolkits/axisartist/axisline_style.py:docstring of mpl_toolkits.axisartist.axisline_style.AxislineStyle:1"
    ],
    "matplotlib.projections.geo.AitoffAxes": [
      "doc/api/artist_api.rst:189"
    ],
    "matplotlib.projections.geo.GeoAxes": [
      "doc/api/artist_api.rst:189"
    ],
    "matplotlib.projections.geo.HammerAxes": [
      "doc/api/artist_api.rst:189"
    ],
    "matplotlib.projections.geo.LambertAxes": [
      "doc/api/artist_api.rst:189"
    ],
    "matplotlib.projections.geo.MollweideAxes": [
      "doc/api/artist_api.rst:189"
    ],
    "matplotlib.text._AnnotationBase": [
      "doc/api/artist_api.rst:189",
      "lib/matplotlib/offsetbox.py:docstring of matplotlib.offsetbox.AnnotationBbox:1",
      "lib/matplotlib/text.py:docstring of matplotlib.text.Annotation:1"
    ],
    "matplotlib.transforms._BlendedMixin": [
      "lib/matplotlib/transforms.py:docstring of matplotlib.transforms.BlendedAffine2D:1",
      "lib/matplotlib/transforms.py:docstring of matplotlib.transforms.BlendedGenericTransform:1"
    ],
    "matplotlib.tri.trifinder.TriFinder": [
      "lib/matplotlib/tri/trifinder.py:docstring of matplotlib.tri.TrapezoidMapTriFinder:1"
    ],
    "matplotlib.tri.triinterpolate.TriInterpolator": [
      "lib/matplotlib/tri/triinterpolate.py:docstring of matplotlib.tri.CubicTriInterpolator:1",
      "lib/matplotlib/tri/triinterpolate.py:docstring of matplotlib.tri.LinearTriInterpolator:1"
    ],
    "matplotlib.tri.trirefine.TriRefiner": [
      "lib/matplotlib/tri/trirefine.py:docstring of matplotlib.tri.UniformTriRefiner:1"
    ],
    "matplotlib.widgets._SelectorWidget": [
      "lib/matplotlib/widgets.py:docstring of matplotlib.widgets.LassoSelector:1",
      "lib/matplotlib/widgets.py:docstring of matplotlib.widgets.PolygonSelector:1",
      "lib/matplotlib/widgets.py:docstring of matplotlib.widgets.RectangleSelector:1",
      "lib/matplotlib/widgets.py:docstring of matplotlib.widgets.SpanSelector:1"
    ],
    "mpl_toolkits.axes_grid1.axes_size._Base": [
      "lib/mpl_toolkits/axes_grid1/axes_size.py:docstring of mpl_toolkits.axes_grid1.axes_size.Add:1",
      "lib/mpl_toolkits/axes_grid1/axes_size.py:docstring of mpl_toolkits.axes_grid1.axes_size.AddList:1",
      "lib/mpl_toolkits/axes_grid1/axes_size.py:docstring of mpl_toolkits.axes_grid1.axes_size.AxesX:1",
      "lib/mpl_toolkits/axes_grid1/axes_size.py:docstring of mpl_toolkits.axes_grid1.axes_size.AxesY:1",
      "lib/mpl_toolkits/axes_grid1/axes_size.py:docstring of mpl_toolkits.axes_grid1.axes_size.Fixed:1",
      "lib/mpl_toolkits/axes_grid1/axes_size.py:docstring of mpl_toolkits.axes_grid1.axes_size.Fraction:1",
      "lib/mpl_toolkits/axes_grid1/axes_size.py:docstring of mpl_toolkits.axes_grid1.axes_size.MaxExtent:1",
      "lib/mpl_toolkits/axes_grid1/axes_size.py:docstring of mpl_toolkits.axes_grid1.axes_size.Padded:1",
      "lib/mpl_toolkits/axes_grid1/axes_size.py:docstring of mpl_toolkits.axes_grid1.axes_size.Scaled:1",
      "lib/mpl_toolkits/axes_grid1/axes_size.py:docstring of mpl_toolkits.axes_grid1.axes_size.SizeFromFunc:1"
    ],
    "mpl_toolkits.axes_grid1.parasite_axes.AxesHostAxes": [
      "<unknown>:1",
      "doc/api/_as_gen/mpl_toolkits.axes_grid1.parasite_axes.rst:31:<autosummary>:1"
    ],
    "mpl_toolkits.axes_grid1.parasite_axes.AxesParasite": [
      "<unknown>:1",
      "doc/api/_as_gen/mpl_toolkits.axes_grid1.parasite_axes.rst:31:<autosummary>:1"
    ],
    "mpl_toolkits.axes_grid1.parasite_axes.AxesParasiteParasiteAuxTrans": [
      "<unknown>:1",
      "doc/api/_as_gen/mpl_toolkits.axes_grid1.parasite_axes.rst:31:<autosummary>:1"
    ],
    "mpl_toolkits.axisartist.Axes": [
      "doc/api/toolkits/axisartist.rst:5",
      "doc/api/toolkits/axisartist.rst:6"
    ],
    "mpl_toolkits.axisartist.axisline_style.AxislineStyle._Base": [
      "lib/mpl_toolkits/axisartist/axisline_style.py:docstring of mpl_toolkits.axisartist.axisline_style.AxislineStyle.SimpleArrow:1"
    ],
    "mpl_toolkits.axisartist.axislines.AxisArtistHelper._Base": [
      "lib/mpl_toolkits/axisartist/axislines.py:docstring of mpl_toolkits.axisartist.axislines.AxisArtistHelper.Fixed:1",
      "lib/mpl_toolkits/axisartist/axislines.py:docstring of mpl_toolkits.axisartist.axislines.AxisArtistHelper.Floating:1"
    ],
    "mpl_toolkits.axisartist.floating_axes.Floating AxesHostAxes": [
      "<unknown>:1",
      "doc/api/_as_gen/mpl_toolkits.axisartist.floating_axes.rst:31:<autosummary>:1"
    ],
    "numpy.uint8": [
      "<unknown>:1"
    ],
    "unittest.case.TestCase": [
      "lib/matplotlib/testing/decorators.py:docstring of matplotlib.testing.decorators.CleanupTestCase:1"
    ]
  },
  "py:data": {
    "matplotlib.axes.Axes.transAxes": [
      "lib/matplotlib/axes/_axes.py:docstring of matplotlib.axes.Axes.legend:213",
      "lib/matplotlib/figure.py:docstring of matplotlib.figure.Figure.legend:177",
      "lib/matplotlib/legend.py:docstring of matplotlib.legend.Legend:172",
      "lib/matplotlib/pyplot.py:docstring of matplotlib.pyplot.figlegend:177",
      "lib/matplotlib/pyplot.py:docstring of matplotlib.pyplot.legend:213"
    ]
  },
  "py:func": {
    "log.debug": [
      "doc/devel/contributing.rst:450"
    ],
    "matplotlib.Axis.set_ticks_position": [
      "doc/users/prev_whats_new/whats_new_1.4.rst:141"
    ],
    "matplotlib.InvertedPolarTransform.transform_non_affine": [
      "doc/users/prev_whats_new/whats_new_1.4.rst:236"
    ],
    "matplotlib.axis.Tick.label1On": [
      "doc/users/prev_whats_new/whats_new_2.1.0.rst:409"
    ],
    "matplotlib.test": [
      "doc/devel/testing.rst:79"
    ],
    "matplotlib.testing.conftest.mpl_test_settings": [
      "doc/devel/testing.rst:106"
    ]
  },
  "py:meth": {
    "AbstractPathEffect._update_gc": [
      "lib/matplotlib/patheffects.py:docstring of matplotlib.patheffects.SimpleLineShadow:43",
      "lib/matplotlib/patheffects.py:docstring of matplotlib.patheffects.SimplePatchShadow:42",
      "lib/matplotlib/patheffects.py:docstring of matplotlib.patheffects.withSimplePatchShadow:51"
    ],
    "Colormap.__call__": [
      "lib/matplotlib/colors.py:docstring of matplotlib.colors.BoundaryNorm:44"
    ],
    "FigureCanvasQTAgg.blit": [
      "doc/api/prev_api_changes/api_changes_2.2.0.rst:199"
    ],
    "FigureCanvasQTAgg.paintEvent": [
      "doc/api/prev_api_changes/api_changes_2.2.0.rst:199"
    ],
    "FigureCanvasQTAgg.print_figure": [
      "doc/api/prev_api_changes/api_changes_2.2.0.rst:199"
    ],
    "_find_tails": [
      "lib/matplotlib/quiver.py:docstring of matplotlib.quiver.Barbs:9"
    ],
    "_init_toolbar": [
      "lib/matplotlib/backend_bases.py:docstring of matplotlib.backend_bases.NavigationToolbar2:17"
    ],
    "_iter_collection": [
      "lib/matplotlib/backend_bases.py:docstring of matplotlib.backend_bases.RendererBase.draw_path_collection:10",
      "lib/matplotlib/backends/backend_pdf.py:docstring of matplotlib.backends.backend_pdf.RendererPdf.draw_path_collection:10",
      "lib/matplotlib/backends/backend_ps.py:docstring of matplotlib.backends.backend_ps.RendererPS.draw_path_collection:10",
      "lib/matplotlib/backends/backend_svg.py:docstring of matplotlib.backends.backend_svg.RendererSVG.draw_path_collection:10",
      "lib/matplotlib/patheffects.py:docstring of matplotlib.patheffects.PathEffectRenderer.draw_path_collection:10"
    ],
    "_iter_collection_raw_paths": [
      "lib/matplotlib/backend_bases.py:docstring of matplotlib.backend_bases.RendererBase.draw_path_collection:10",
      "lib/matplotlib/backends/backend_pdf.py:docstring of matplotlib.backends.backend_pdf.RendererPdf.draw_path_collection:10",
      "lib/matplotlib/backends/backend_ps.py:docstring of matplotlib.backends.backend_ps.RendererPS.draw_path_collection:10",
      "lib/matplotlib/backends/backend_svg.py:docstring of matplotlib.backends.backend_svg.RendererSVG.draw_path_collection:10",
      "lib/matplotlib/patheffects.py:docstring of matplotlib.patheffects.PathEffectRenderer.draw_path_collection:10"
    ],
    "_make_barbs": [
      "lib/matplotlib/quiver.py:docstring of matplotlib.quiver.Barbs:9"
    ],
    "_process_colors": [
      "lib/matplotlib/contour.py:docstring of matplotlib.contour.ContourSet:64",
      "lib/matplotlib/contour.py:docstring of matplotlib.contour.QuadContourSet:30"
    ],
    "autoscale_view": [
      "lib/matplotlib/pyplot.py:docstring of matplotlib.pyplot.margins:32"
    ],
    "colorbar.Colobar.minorticks_off": [
      "doc/users/prev_whats_new/whats_new_3.0.rst:63"
    ],
    "colorbar.Colobar.minorticks_on": [
      "doc/users/prev_whats_new/whats_new_3.0.rst:63"
    ],
    "draw_image": [
      "lib/matplotlib/backends/backend_agg.py:docstring of matplotlib.backends.backend_agg.RendererAgg.option_scale_image:2"
    ],
    "get_matrix": [
      "lib/matplotlib/transforms.py:docstring of matplotlib.transforms.Affine2DBase:13"
    ],
    "matplotlib.dates.DateFormatter.__call__": [
      "doc/users/prev_whats_new/whats_new_1.5.rst:497"
    ],
    "matplotlib.dates.MicrosecondLocator.__call__": [
      "doc/api/prev_api_changes/api_changes_1.5.0.rst:122"
    ],
    "matplotlib.lines.Line2D.pick": [
      "doc/users/event_handling.rst:480"
    ],
    "matplotlib.patches.Rectangle.contains": [
      "doc/users/event_handling.rst:164"
    ],
    "matplotlib.text.Text.__init__": [
      "doc/devel/contributing.rst:400",
      "doc/devel/contributing.rst:408"
    ],
    "option_scale_image": [
      "lib/matplotlib/backends/backend_cairo.py:docstring of matplotlib.backends.backend_cairo.RendererCairo.draw_image:22",
      "lib/matplotlib/backends/backend_pdf.py:docstring of matplotlib.backends.backend_pdf.RendererPdf.draw_image:22",
      "lib/matplotlib/backends/backend_ps.py:docstring of matplotlib.backends.backend_ps.RendererPS.draw_image:22",
      "lib/matplotlib/backends/backend_template.py:docstring of matplotlib.backends.backend_template.RendererTemplate.draw_image:22"
    ],
    "set_label": [
      "lib/mpl_toolkits/axes_grid1/colorbar.py:docstring of mpl_toolkits.axes_grid1.colorbar.ColorbarBase:31"
    ]
  },
  "py:mod": {
    "dateutil": [
      "lib/matplotlib/dates.py:docstring of matplotlib.dates:1"
    ],
    "matplotlib": [
      "doc/api/prev_api_changes/api_changes_0.91.2.rst:15"
    ],
    "matplotlib.backends.backend_gtk3agg": [
      "doc/api/backend_gtk3agg_api.rst:2"
    ],
    "matplotlib.backends.backend_gtk3cairo": [
      "doc/api/backend_gtk3cairo_api.rst:2"
    ],
    "matplotlib.backends.backend_qt4agg": [
      "doc/api/backend_qt4agg_api.rst:2"
    ],
    "matplotlib.backends.backend_qt4cairo": [
      "doc/api/backend_qt4cairo_api.rst:2"
    ],
    "matplotlib.backends.backend_qt5agg": [
      "doc/api/backend_qt5agg_api.rst:2"
    ],
    "matplotlib.backends.backend_qt5cairo": [
      "doc/api/backend_qt5cairo_api.rst:2"
    ],
    "matplotlib.backends.backend_webagg": [
      "doc/api/backend_webagg_api.rst:2"
    ],
    "matplotlib.backends.backend_wxagg": [
      "doc/api/backend_wxagg_api.rst:2"
    ],
    "matplotlib.ft2font": [
      "doc/api/prev_api_changes/api_changes_0.91.0.rst:34"
    ],
    "matplotlib.tests.test_basic": [
      "doc/devel/testing.rst:93"
    ]
  },
  "py:obj": {
    "./gallery/index.html": [
      "doc/devel/contributing.rst:562"
    ],
    "Artist.sticky_edges": [
      "doc/api/axes_api.rst:362:<autosummary>:1",
      "lib/matplotlib/axes/_axes.py:docstring of matplotlib.axes.Axes.use_sticky_edges:2"
    ],
    "ArtistInspector.aliasd": [
      "doc/api/prev_api_changes/api_changes_3.0.0.rst:332",
      "doc/users/prev_whats_new/whats_new_3.1.0.rst:171"
    ],
    "ArtistInspector.get_aliases": [
      "doc/api/prev_api_changes/api_changes_3.0.0.rst:327"
    ],
    "Artists": [
      "lib/matplotlib/offsetbox.py:docstring of matplotlib.offsetbox.HPacker:44",
      "lib/matplotlib/offsetbox.py:docstring of matplotlib.offsetbox.PackerBase:23",
      "lib/matplotlib/offsetbox.py:docstring of matplotlib.offsetbox.VPacker:44"
    ],
    "Axes..set_inverted": [
      "doc/users/prev_whats_new/whats_new_3.1.0.rst:247"
    ],
    "Axes.dataLim": [
      "doc/api/axes_api.rst:302:<autosummary>:1",
      "lib/matplotlib/axes/_base.py:docstring of matplotlib.axes.Axes.update_datalim:2",
      "lib/mpl_toolkits/mplot3d/axes3d.py:docstring of mpl_toolkits.mplot3d.axes3d.Axes3D.update_datalim:2"
    ],
    "Axes.datalim": [
      "doc/api/axes_api.rst:302:<autosummary>:1",
      "lib/matplotlib/axes/_base.py:docstring of matplotlib.axes.Axes.update_datalim_bounds:2"
    ],
    "Axes.fmt_xdata": [
      "doc/api/prev_api_changes/api_changes_3.1.0.rst:397",
      "doc/api/prev_api_changes/api_changes_3.1.0.rst:400"
    ],
    "Axes.fmt_ydata": [
      "doc/api/prev_api_changes/api_changes_3.1.0.rst:397",
      "doc/api/prev_api_changes/api_changes_3.1.0.rst:400"
    ],
    "Axes.transData": [
      "doc/api/prev_api_changes/api_changes_3.2.0/behavior.rst:89",
      "doc/api/prev_api_changes/api_changes_3.2.0/behavior.rst:91",
      "doc/api/prev_api_changes/api_changes_3.2.0/behavior.rst:93",
      "doc/api/prev_api_changes/api_changes_3.2.0/behavior.rst:96"
    ],
    "AxesBase": [
      "doc/api/axes_api.rst:454:<autosummary>:1",
      "lib/matplotlib/axes/_base.py:docstring of matplotlib.axes.Axes.add_child_axes:2"
    ],
    "Axis._update_ticks": [
      "doc/api/prev_api_changes/api_changes_3.1.0.rst:1066"
    ],
    "Axis.get_inverted": [
      "doc/users/prev_whats_new/whats_new_3.1.0.rst:241",
      "doc/users/prev_whats_new/whats_new_3.1.0.rst:243"
    ],
    "Axis.remove_overlaping_locs": [
      "doc/api/prev_api_changes/api_changes_3.1.0.rst:71"
    ],
    "Axis.set_inverted": [
      "doc/users/prev_whats_new/whats_new_3.1.0.rst:241",
      "doc/users/prev_whats_new/whats_new_3.1.0.rst:243"
    ],
    "Axis.set_tick_params": [
      "doc/users/prev_whats_new/whats_new_2.1.0.rst:394"
    ],
    "Axis.units": [
      "doc/api/prev_api_changes/api_changes_2.2.0.rst:77"
    ],
    "Canvas": [
      "doc/devel/MEP/MEP22.rst:56",
      "doc/devel/MEP/MEP22.rst:60",
      "doc/devel/MEP/MEP23.rst:70"
    ],
    "ConnectionPatch": [
      "doc/users/prev_whats_new/whats_new_3.1.0.rst:178"
    ],
    "FT2Font": [
      "doc/gallery/misc/ftface_props.rst:16",
      "lib/matplotlib/font_manager.py:docstring of matplotlib.font_manager.ttfFontProperty:8"
    ],
    "FigureCanvas": [
      "lib/matplotlib/backend_tools.py:docstring of matplotlib.backend_tools.ToolBase:25"
    ],
    "FigureManager": [
      "doc/devel/MEP/MEP23.rst:25",
      "doc/devel/MEP/MEP23.rst:62",
      "doc/devel/MEP/MEP23.rst:63",
      "doc/devel/MEP/MEP23.rst:65",
      "doc/devel/MEP/MEP23.rst:78",
      "doc/devel/MEP/MEP23.rst:85",
      "doc/devel/MEP/MEP23.rst:87"
    ],
    "Formatter.__call__": [
      "doc/api/prev_api_changes/api_changes_3.1.0.rst:1115",
      "doc/api/prev_api_changes/api_changes_3.1.0.rst:1121"
    ],
    "GaussianKDE": [
      "lib/matplotlib/axes/_axes.py:docstring of matplotlib.axes.Axes.violinplot:46",
      "lib/matplotlib/pyplot.py:docstring of matplotlib.pyplot.violinplot:46"
    ],
    "Glyph": [
      "doc/gallery/misc/ftface_props.rst:16"
    ],
    "GraphicsContext": [
      "doc/devel/MEP/MEP26.rst:68"
    ],
    "Image": [
      "lib/matplotlib/pyplot.py:docstring of matplotlib.pyplot.gci:4"
    ],
    "ImageComparisonFailure": [
      "lib/matplotlib/testing/decorators.py:docstring of matplotlib.testing.decorators.image_comparison:2"
    ],
    "ImageComparisonTest": [
      "doc/api/prev_api_changes/api_changes_3.1.0.rst:702"
    ],
    "MicrosecondLocator.__call__": [
      "doc/api/prev_api_changes/api_changes_1.5.0.rst:119"
    ],
    "MovieWriter.saving": [
      "doc/api/animation_api.rst:221"
    ],
    "MovieWriterBase": [
      "lib/matplotlib/animation.py:docstring of matplotlib.animation.AVConvBase:4",
      "lib/matplotlib/animation.py:docstring of matplotlib.animation.FFMpegBase:4",
      "lib/matplotlib/animation.py:docstring of matplotlib.animation.ImageMagickBase:4"
    ],
    "MovieWriterRegistry": [
      "doc/api/prev_api_changes/api_changes_3.2.0/behavior.rst:49",
      "doc/api/prev_api_changes/api_changes_3.2.0/behavior.rst:51",
      "doc/api/prev_api_changes/api_changes_3.2.0/deprecations.rst:121"
    ],
    "Navigation": [
      "doc/devel/MEP/MEP22.rst:155",
      "doc/devel/MEP/MEP22.rst:60"
    ],
    "NavigationBase": [
      "doc/devel/MEP/MEP23.rst:90",
      "doc/devel/MEP/MEP23.rst:93"
    ],
    "NavigationToolbar2QT.adj_window": [
      "doc/api/prev_api_changes/api_changes_3.1.0.rst:961"
    ],
    "PolyCollection.get_offset": [
      "lib/matplotlib/axes/_axes.py:docstring of matplotlib.axes.Axes.hexbin:71",
      "lib/matplotlib/pyplot.py:docstring of matplotlib.pyplot.hexbin:71"
    ],
    "QuadContourSet.changed()": [
      "lib/matplotlib/axes/_axes.py:docstring of matplotlib.axes.Axes.contour:131",
      "lib/matplotlib/axes/_axes.py:docstring of matplotlib.axes.Axes.contourf:131",
      "lib/matplotlib/pyplot.py:docstring of matplotlib.pyplot.contour:131",
      "lib/matplotlib/pyplot.py:docstring of matplotlib.pyplot.contourf:131"
    ],
    "Quit": [
      "doc/devel/MEP/MEP22.rst:78"
    ],
    "Quiver.pivot": [
      "doc/api/prev_api_changes/api_changes_1.5.0.rst:44"
    ],
    "Size.from_any": [
      "lib/mpl_toolkits/axes_grid1/axes_grid.py:docstring of mpl_toolkits.axes_grid1.axes_grid.ImageGrid:61",
      "lib/mpl_toolkits/axisartist/axes_grid.py:docstring of mpl_toolkits.axisartist.axes_grid.ImageGrid:61"
    ],
    "Style": [
      "doc/devel/MEP/MEP26.rst:68"
    ],
    "SubplotTool": [
      "doc/devel/MEP/MEP22.rst:78"
    ],
    "TextFont": [
      "doc/devel/MEP/MEP14.rst:267"
    ],
    "TextLayout": [
      "doc/devel/MEP/MEP14.rst:267",
      "doc/devel/MEP/MEP14.rst:376"
    ],
    "TextSpan": [
      "doc/devel/MEP/MEP14.rst:267"
    ],
    "TextSpans": [
      "doc/devel/MEP/MEP14.rst:267"
    ],
    "Timer": [
      "lib/matplotlib/backend_bases.py:docstring of matplotlib.backend_bases.FigureCanvasBase.new_timer:2",
      "lib/matplotlib/backend_bases.py:docstring of matplotlib.backend_bases.TimerBase:14"
    ],
    "Tool": [
      "doc/devel/MEP/MEP22.rst:60",
      "doc/devel/MEP/MEP22.rst:96"
    ],
    "ToolContainer": [
      "doc/users/prev_whats_new/whats_new_1.5.rst:615",
      "lib/matplotlib/backend_bases.py:docstring of matplotlib.backend_bases.ToolContainerBase.remove_toolitem:2",
      "lib/matplotlib/backend_bases.py:docstring of matplotlib.backend_bases.ToolContainerBase:20"
    ],
    "ToolContainers": [
      "doc/users/prev_whats_new/whats_new_1.5.rst:615"
    ],
    "Toolbar": [
      "doc/devel/MEP/MEP22.rst:177",
      "doc/devel/MEP/MEP22.rst:56",
      "doc/devel/MEP/MEP22.rst:60",
      "doc/devel/MEP/MEP23.rst:46"
    ],
    "Toolbars": [
      "doc/users/prev_whats_new/whats_new_1.5.rst:615"
    ],
    "Tools": [
      "doc/devel/MEP/MEP22.rst:40",
      "doc/devel/MEP/MEP22.rst:56",
      "doc/users/prev_whats_new/whats_new_1.5.rst:608"
    ],
    "_read": [
      "lib/matplotlib/dviread.py:docstring of matplotlib.dviread.Vf:20"
    ],
    "active": [
      "lib/matplotlib/widgets.py:docstring of matplotlib.widgets.AxesWidget:34"
    ],
    "add_canvas": [
      "doc/devel/MEP/MEP23.rst:62"
    ],
    "add_subplot": [
      "lib/matplotlib/pyplot.py:docstring of matplotlib.pyplot.subplot2grid:23"
    ],
    "add_tool": [
      "lib/matplotlib/backend_tools.py:docstring of matplotlib.backend_tools.add_tools_to_container:11",
      "lib/matplotlib/backend_tools.py:docstring of matplotlib.backend_tools.add_tools_to_manager:11"
    ],
    "autoscale_view": [
      "lib/matplotlib/pyplot.py:docstring of matplotlib.pyplot.autoscale:19",
      "lib/matplotlib/pyplot.py:docstring of matplotlib.pyplot.plot:121"
    ],
    "ax.transAxes": [
      "lib/matplotlib/axes/_axes.py:docstring of matplotlib.axes.Axes.indicate_inset:19",
      "lib/matplotlib/axes/_axes.py:docstring of matplotlib.axes.Axes.inset_axes:11"
    ],
    "axes.Axes.patch": [
      "doc/api/prev_api_changes/api_changes_1.3.x.rst:36"
    ],
    "axes.bbox": [
      "lib/matplotlib/axes/_axes.py:docstring of matplotlib.axes.Axes.legend:128",
      "lib/matplotlib/figure.py:docstring of matplotlib.figure.Figure.legend:92",
      "lib/matplotlib/legend.py:docstring of matplotlib.legend.Legend:87",
      "lib/matplotlib/pyplot.py:docstring of matplotlib.pyplot.figlegend:92",
      "lib/matplotlib/pyplot.py:docstring of matplotlib.pyplot.legend:128"
    ],
    "axes.prop_cycle": [
      "doc/users/prev_whats_new/whats_new_3.0.rst:111"
    ],
    "axes3d.Axes3D.xaxis": [
      "doc/api/prev_api_changes/api_changes_3.1.0.rst:933"
    ],
    "axes3d.Axes3D.yaxis": [
      "doc/api/prev_api_changes/api_changes_3.1.0.rst:933"
    ],
    "axes3d.Axes3D.zaxis": [
      "doc/api/prev_api_changes/api_changes_3.1.0.rst:933"
    ],
    "axis.Axis.get_ticks_position": [
      "doc/api/prev_api_changes/api_changes_3.1.0.rst:821"
    ],
    "backend_bases.RendererBase": [
      "lib/matplotlib/backends/backend_template.py:docstring of matplotlib.backends.backend_template.RendererTemplate:4"
    ],
    "backend_bases.Timer.add_callback": [
      "doc/api/prev_api_changes/api_changes_3.1.0.rst:259"
    ],
    "backend_bases.Timer.remove_callback": [
      "doc/api/prev_api_changes/api_changes_3.1.0.rst:239"
    ],
    "backend_bases.ToolContainerBase": [
      "lib/matplotlib/backend_tools.py:docstring of matplotlib.backend_tools.add_tools_to_container:8"
    ],
    "backend_gtk3.FileChooserDialog": [
      "doc/api/prev_api_changes/api_changes_3.1.0.rst:958"
    ],
    "backend_gtk3.NavigationToolbar2GTK3.get_filechooser": [
      "doc/api/prev_api_changes/api_changes_3.1.0.rst:959"
    ],
    "backend_gtk3.SaveFigureGTK3.get_filechooser": [
      "doc/api/prev_api_changes/api_changes_3.1.0.rst:960"
    ],
    "backend_wx.IDLE_DELAY": [
      "doc/api/prev_api_changes/api_changes_3.1.0.rst:962"
    ],
    "barstacked": [
      "doc/users/prev_whats_new/whats_new_1.2.rst:177"
    ],
    "bezier.check_if_parallel": [
      "doc/api/prev_api_changes/api_changes_3.1.0.rst:793"
    ],
    "bezier.find_bezier_t_intersecting_with_closedpath": [
      "doc/api/prev_api_changes/api_changes_3.1.0.rst:793"
    ],
    "bezier.find_r_to_boundary_of_closedpath": [
      "doc/api/prev_api_changes/api_changes_3.1.0.rst:1018",
      "doc/api/prev_api_changes/api_changes_3.1.0.rst:793"
    ],
    "bezier.split_bezier_intersecting_with_closedpath": [
      "doc/api/prev_api_changes/api_changes_3.1.0.rst:793"
    ],
    "bezier.split_path_inout": [
      "doc/api/prev_api_changes/api_changes_3.1.0.rst:793"
    ],
    "blocking_input.BlockingInput.__call__": [
      "doc/api/prev_api_changes/api_changes_3.2.0/behavior.rst:293"
    ],
    "calculate_rms": [
      "lib/matplotlib/testing/compare.py:docstring of matplotlib.testing.compare.compare_images:4"
    ],
    "can_composite": [
      "lib/matplotlib/image.py:docstring of matplotlib.image.composite_images:9"
    ],
    "canvas": [
      "doc/devel/MEP/MEP22.rst:140",
      "doc/devel/MEP/MEP23.rst:40"
    ],
    "cbook._warn_external": [
      "doc/devel/contributing.rst:493",
      "doc/devel/contributing.rst:508",
      "doc/devel/contributing.rst:517",
      "doc/devel/contributing.rst:542"
    ],
    "cbook.deprecated": [
      "doc/api/prev_api_changes/api_changes_3.1.0.rst:1073",
      "doc/api/prev_api_changes/api_changes_3.1.0.rst:766"
    ],
    "cbook.warn_deprecated": [
      "doc/api/prev_api_changes/api_changes_3.1.0.rst:766"
    ],
    "cleanup": [
      "lib/matplotlib/animation.py:docstring of matplotlib.animation.HTMLWriter.setup:19"
    ],
    "collections.LineCollection.get_segements()": [
      "doc/api/prev_api_changes/api_changes_3.1.0.rst:280"
    ],
    "colorbar.ColorbarBase.outline": [
      "doc/api/prev_api_changes/api_changes_1.4.x.rst:83"
    ],
    "converter": [
      "lib/matplotlib/testing/compare.py:docstring of matplotlib.testing.compare.compare_images:4"
    ],
    "fc-list": [
      "lib/matplotlib/font_manager.py:docstring of matplotlib.font_manager.get_fontconfig_fonts:2"
    ],
    "figure.Figure.canvas.set_window_title()": [
      "doc/users/prev_whats_new/whats_new_3.0.rst:85"
    ],
    "figure.bbox": [
      "lib/matplotlib/axes/_axes.py:docstring of matplotlib.axes.Axes.legend:128",
      "lib/matplotlib/figure.py:docstring of matplotlib.figure.Figure.legend:92",
      "lib/matplotlib/legend.py:docstring of matplotlib.legend.Legend:87",
      "lib/matplotlib/pyplot.py:docstring of matplotlib.pyplot.figlegend:92",
      "lib/matplotlib/pyplot.py:docstring of matplotlib.pyplot.legend:128"
    ],
    "floating_axes.FloatingSubplot": [
      "doc/gallery/axisartist/demo_floating_axes.rst:22"
    ],
    "fmt_xdata": [
      "lib/matplotlib/axes/_base.py:docstring of matplotlib.axes.Axes.format_xdata:4"
    ],
    "fmt_ydata": [
      "lib/matplotlib/axes/_base.py:docstring of matplotlib.axes.Axes.format_ydata:4"
    ],
    "font.*": [
      "doc/users/prev_whats_new/whats_new_1.3.rst:302"
    ],
    "gaussian_kde": [
      "lib/matplotlib/mlab.py:docstring of matplotlib.mlab.GaussianKDE:32"
    ],
    "get_active_canvas": [
      "doc/devel/MEP/MEP23.rst:70"
    ],
    "get_canvas_title": [
      "doc/devel/MEP/MEP23.rst:68"
    ],
    "get_ps": [
      "doc/devel/MEP/MEP14.rst:376"
    ],
    "get_size": [
      "doc/users/prev_whats_new/whats_new_1.4.rst:223",
      "lib/mpl_toolkits/axes_grid1/axes_size.py:docstring of mpl_toolkits.axes_grid1.axes_size:1"
    ],
    "get_spans": [
      "doc/devel/MEP/MEP14.rst:376"
    ],
    "get_xbound": [
      "lib/mpl_toolkits/mplot3d/axes3d.py:docstring of mpl_toolkits.mplot3d.axes3d.Axes3D.get_xlim3d:22"
    ],
    "get_ybound": [
      "lib/mpl_toolkits/mplot3d/axes3d.py:docstring of mpl_toolkits.mplot3d.axes3d.Axes3D.get_ylim3d:22"
    ],
    "h_pad": [
      "lib/matplotlib/figure.py:docstring of matplotlib.figure.Figure.set_constrained_layout:5"
    ],
    "image": [
      "lib/matplotlib/sphinxext/plot_directive.py:docstring of matplotlib.sphinxext.plot_directive:73"
    ],
    "interactive": [
      "lib/matplotlib/backends/backend_nbagg.py:docstring of matplotlib.backends.backend_nbagg.show:4"
    ],
    "invert_xaxis": [
      "lib/mpl_toolkits/mplot3d/axes3d.py:docstring of mpl_toolkits.mplot3d.axes3d.Axes3D.get_xlim3d:24"
    ],
    "invert_yaxis": [
      "lib/mpl_toolkits/mplot3d/axes3d.py:docstring of mpl_toolkits.mplot3d.axes3d.Axes3D.get_ylim3d:24"
    ],
    "kde.covariance_factor": [
      "lib/matplotlib/mlab.py:docstring of matplotlib.mlab.GaussianKDE:41"
    ],
    "kde.factor": [
      "lib/matplotlib/axes/_axes.py:docstring of matplotlib.axes.Axes.violinplot:46",
      "lib/matplotlib/mlab.py:docstring of matplotlib.mlab.GaussianKDE:12",
      "lib/matplotlib/mlab.py:docstring of matplotlib.mlab.GaussianKDE:45",
      "lib/matplotlib/pyplot.py:docstring of matplotlib.pyplot.violinplot:46"
    ],
    "labelcolor": [
      "doc/users/prev_whats_new/whats_new_2.0.0.rst:120",
      "doc/users/prev_whats_new/whats_new_2.0.0.rst:123"
    ],
    "legend.Legend.set_draggable()": [
      "doc/api/prev_api_changes/api_changes_3.1.0.rst:499"
    ],
    "levels": [
      "doc/api/prev_api_changes/api_changes_3.0.0.rst:197"
    ],
    "load_char": [
      "doc/gallery/misc/ftface_props.rst:16"
    ],
    "logging.WARNING": [
      "doc/devel/contributing.rst:468",
      "doc/devel/contributing.rst:505"
    ],
    "ls_mapper": [
      "doc/api/prev_api_changes/api_changes_1.5.0.rst:11"
    ],
    "ls_mapper_r": [
      "doc/api/prev_api_changes/api_changes_1.5.0.rst:11",
      "doc/api/prev_api_changes/api_changes_1.5.0.rst:8"
    ],
    "mainloop": [
      "lib/matplotlib/backends/backend_nbagg.py:docstring of matplotlib.backends.backend_nbagg.show:4"
    ],
    "make_image": [
      "lib/matplotlib/image.py:docstring of matplotlib.image.composite_images:9"
    ],
    "markevery": [
      "doc/users/prev_whats_new/whats_new_1.4.rst:212",
      "doc/users/prev_whats_new/whats_new_1.4.rst:214",
      "doc/users/prev_whats_new/whats_new_3.0.rst:111"
    ],
    "matplotlib.Axes.bar": [
      "doc/users/dflt_style_changes.rst:609"
    ],
    "matplotlib.Axes.barh": [
      "doc/users/dflt_style_changes.rst:609"
    ],
    "matplotlib.Axes.hexbin": [
      "doc/users/dflt_style_changes.rst:600"
    ],
    "matplotlib.Figure.set_size_inches": [
      "doc/users/dflt_style_changes.rst:262"
    ],
    "matplotlib.animation.AVConvBase.output_args": [
      "lib/matplotlib/animation.py:docstring of matplotlib.animation.AVConvBase.isAvailable:1:<autosummary>:1"
    ],
    "matplotlib.animation.AVConvFileWriter.args_key": [
      "doc/api/_as_gen/matplotlib.animation.AVConvFileWriter.rst:39:<autosummary>:1"
    ],
    "matplotlib.animation.AVConvFileWriter.bin_path": [
      "doc/api/_as_gen/matplotlib.animation.AVConvFileWriter.rst:28:<autosummary>:1"
    ],
    "matplotlib.animation.AVConvFileWriter.cleanup": [
      "doc/api/_as_gen/matplotlib.animation.AVConvFileWriter.rst:28:<autosummary>:1"
    ],
    "matplotlib.animation.AVConvFileWriter.clear_temp": [
      "doc/api/_as_gen/matplotlib.animation.AVConvFileWriter.rst:39:<autosummary>:1"
    ],
    "matplotlib.animation.AVConvFileWriter.exec_key": [
      "doc/api/_as_gen/matplotlib.animation.AVConvFileWriter.rst:39:<autosummary>:1"
    ],
    "matplotlib.animation.AVConvFileWriter.finish": [
      "doc/api/_as_gen/matplotlib.animation.AVConvFileWriter.rst:28:<autosummary>:1"
    ],
    "matplotlib.animation.AVConvFileWriter.frame_format": [
      "doc/api/_as_gen/matplotlib.animation.AVConvFileWriter.rst:39:<autosummary>:1"
    ],
    "matplotlib.animation.AVConvFileWriter.frame_size": [
      "doc/api/_as_gen/matplotlib.animation.AVConvFileWriter.rst:39:<autosummary>:1"
    ],
    "matplotlib.animation.AVConvFileWriter.grab_frame": [
      "doc/api/_as_gen/matplotlib.animation.AVConvFileWriter.rst:28:<autosummary>:1"
    ],
    "matplotlib.animation.AVConvFileWriter.isAvailable": [
      "doc/api/_as_gen/matplotlib.animation.AVConvFileWriter.rst:28:<autosummary>:1"
    ],
    "matplotlib.animation.AVConvFileWriter.output_args": [
      "doc/api/_as_gen/matplotlib.animation.AVConvFileWriter.rst:39:<autosummary>:1"
    ],
    "matplotlib.animation.AVConvFileWriter.saving": [
      "doc/api/_as_gen/matplotlib.animation.AVConvFileWriter.rst:28:<autosummary>:1"
    ],
    "matplotlib.animation.AVConvFileWriter.setup": [
      "doc/api/_as_gen/matplotlib.animation.AVConvFileWriter.rst:28:<autosummary>:1"
    ],
    "matplotlib.animation.AVConvFileWriter.supported_formats": [
      "doc/api/_as_gen/matplotlib.animation.AVConvFileWriter.rst:39:<autosummary>:1"
    ],
    "matplotlib.animation.AVConvWriter.args_key": [
      "doc/api/_as_gen/matplotlib.animation.AVConvWriter.rst:36:<autosummary>:1"
    ],
    "matplotlib.animation.AVConvWriter.bin_path": [
      "doc/api/_as_gen/matplotlib.animation.AVConvWriter.rst:28:<autosummary>:1"
    ],
    "matplotlib.animation.AVConvWriter.cleanup": [
      "doc/api/_as_gen/matplotlib.animation.AVConvWriter.rst:28:<autosummary>:1"
    ],
    "matplotlib.animation.AVConvWriter.exec_key": [
      "doc/api/_as_gen/matplotlib.animation.AVConvWriter.rst:36:<autosummary>:1"
    ],
    "matplotlib.animation.AVConvWriter.finish": [
      "doc/api/_as_gen/matplotlib.animation.AVConvWriter.rst:28:<autosummary>:1"
    ],
    "matplotlib.animation.AVConvWriter.frame_size": [
      "doc/api/_as_gen/matplotlib.animation.AVConvWriter.rst:36:<autosummary>:1"
    ],
    "matplotlib.animation.AVConvWriter.grab_frame": [
      "doc/api/_as_gen/matplotlib.animation.AVConvWriter.rst:28:<autosummary>:1"
    ],
    "matplotlib.animation.AVConvWriter.isAvailable": [
      "doc/api/_as_gen/matplotlib.animation.AVConvWriter.rst:28:<autosummary>:1"
    ],
    "matplotlib.animation.AVConvWriter.output_args": [
      "doc/api/_as_gen/matplotlib.animation.AVConvWriter.rst:36:<autosummary>:1"
    ],
    "matplotlib.animation.AVConvWriter.saving": [
      "doc/api/_as_gen/matplotlib.animation.AVConvWriter.rst:28:<autosummary>:1"
    ],
    "matplotlib.animation.AVConvWriter.setup": [
      "doc/api/_as_gen/matplotlib.animation.AVConvWriter.rst:28:<autosummary>:1"
    ],
    "matplotlib.animation.ArtistAnimation.new_frame_seq": [
      "doc/api/_as_gen/matplotlib.animation.ArtistAnimation.rst:21:<autosummary>:1"
    ],
    "matplotlib.animation.ArtistAnimation.new_saved_frame_seq": [
      "doc/api/_as_gen/matplotlib.animation.ArtistAnimation.rst:21:<autosummary>:1"
    ],
    "matplotlib.animation.ArtistAnimation.save": [
      "doc/api/_as_gen/matplotlib.animation.ArtistAnimation.rst:21:<autosummary>:1"
    ],
    "matplotlib.animation.ArtistAnimation.to_html5_video": [
      "doc/api/_as_gen/matplotlib.animation.ArtistAnimation.rst:21:<autosummary>:1"
    ],
    "matplotlib.animation.ArtistAnimation.to_jshtml": [
      "doc/api/_as_gen/matplotlib.animation.ArtistAnimation.rst:21:<autosummary>:1"
    ],
    "matplotlib.animation.FFMpegFileWriter.args_key": [
      "lib/matplotlib/animation.py:docstring of matplotlib.animation.FFMpegFileWriter.supported_formats:1:<autosummary>:1"
    ],
    "matplotlib.animation.FFMpegFileWriter.bin_path": [
      "doc/api/_as_gen/matplotlib.animation.FFMpegFileWriter.rst:28:<autosummary>:1"
    ],
    "matplotlib.animation.FFMpegFileWriter.cleanup": [
      "doc/api/_as_gen/matplotlib.animation.FFMpegFileWriter.rst:28:<autosummary>:1"
    ],
    "matplotlib.animation.FFMpegFileWriter.clear_temp": [
      "lib/matplotlib/animation.py:docstring of matplotlib.animation.FFMpegFileWriter.supported_formats:1:<autosummary>:1"
    ],
    "matplotlib.animation.FFMpegFileWriter.exec_key": [
      "lib/matplotlib/animation.py:docstring of matplotlib.animation.FFMpegFileWriter.supported_formats:1:<autosummary>:1"
    ],
    "matplotlib.animation.FFMpegFileWriter.finish": [
      "doc/api/_as_gen/matplotlib.animation.FFMpegFileWriter.rst:28:<autosummary>:1"
    ],
    "matplotlib.animation.FFMpegFileWriter.frame_format": [
      "lib/matplotlib/animation.py:docstring of matplotlib.animation.FFMpegFileWriter.supported_formats:1:<autosummary>:1"
    ],
    "matplotlib.animation.FFMpegFileWriter.frame_size": [
      "lib/matplotlib/animation.py:docstring of matplotlib.animation.FFMpegFileWriter.supported_formats:1:<autosummary>:1"
    ],
    "matplotlib.animation.FFMpegFileWriter.grab_frame": [
      "doc/api/_as_gen/matplotlib.animation.FFMpegFileWriter.rst:28:<autosummary>:1"
    ],
    "matplotlib.animation.FFMpegFileWriter.isAvailable": [
      "doc/api/_as_gen/matplotlib.animation.FFMpegFileWriter.rst:28:<autosummary>:1"
    ],
    "matplotlib.animation.FFMpegFileWriter.output_args": [
      "lib/matplotlib/animation.py:docstring of matplotlib.animation.FFMpegFileWriter.supported_formats:1:<autosummary>:1"
    ],
    "matplotlib.animation.FFMpegFileWriter.saving": [
      "doc/api/_as_gen/matplotlib.animation.FFMpegFileWriter.rst:28:<autosummary>:1"
    ],
    "matplotlib.animation.FFMpegFileWriter.setup": [
      "doc/api/_as_gen/matplotlib.animation.FFMpegFileWriter.rst:28:<autosummary>:1"
    ],
    "matplotlib.animation.FFMpegWriter.args_key": [
      "doc/api/_as_gen/matplotlib.animation.FFMpegWriter.rst:36:<autosummary>:1"
    ],
    "matplotlib.animation.FFMpegWriter.bin_path": [
      "doc/api/_as_gen/matplotlib.animation.FFMpegWriter.rst:28:<autosummary>:1"
    ],
    "matplotlib.animation.FFMpegWriter.cleanup": [
      "doc/api/_as_gen/matplotlib.animation.FFMpegWriter.rst:28:<autosummary>:1"
    ],
    "matplotlib.animation.FFMpegWriter.exec_key": [
      "doc/api/_as_gen/matplotlib.animation.FFMpegWriter.rst:36:<autosummary>:1"
    ],
    "matplotlib.animation.FFMpegWriter.finish": [
      "doc/api/_as_gen/matplotlib.animation.FFMpegWriter.rst:28:<autosummary>:1"
    ],
    "matplotlib.animation.FFMpegWriter.frame_size": [
      "doc/api/_as_gen/matplotlib.animation.FFMpegWriter.rst:36:<autosummary>:1"
    ],
    "matplotlib.animation.FFMpegWriter.grab_frame": [
      "doc/api/_as_gen/matplotlib.animation.FFMpegWriter.rst:28:<autosummary>:1"
    ],
    "matplotlib.animation.FFMpegWriter.isAvailable": [
      "doc/api/_as_gen/matplotlib.animation.FFMpegWriter.rst:28:<autosummary>:1"
    ],
    "matplotlib.animation.FFMpegWriter.output_args": [
      "doc/api/_as_gen/matplotlib.animation.FFMpegWriter.rst:36:<autosummary>:1"
    ],
    "matplotlib.animation.FFMpegWriter.saving": [
      "doc/api/_as_gen/matplotlib.animation.FFMpegWriter.rst:28:<autosummary>:1"
    ],
    "matplotlib.animation.FFMpegWriter.setup": [
      "doc/api/_as_gen/matplotlib.animation.FFMpegWriter.rst:28:<autosummary>:1"
    ],
    "matplotlib.animation.FileMovieWriter.args_key": [
      "lib/matplotlib/animation.py:docstring of matplotlib.animation.FileMovieWriter.cleanup:1:<autosummary>:1"
    ],
    "matplotlib.animation.FileMovieWriter.bin_path": [
      "doc/api/_as_gen/matplotlib.animation.FileMovieWriter.rst:28:<autosummary>:1"
    ],
    "matplotlib.animation.FileMovieWriter.exec_key": [
      "lib/matplotlib/animation.py:docstring of matplotlib.animation.FileMovieWriter.cleanup:1:<autosummary>:1"
    ],
    "matplotlib.animation.FileMovieWriter.frame_size": [
      "lib/matplotlib/animation.py:docstring of matplotlib.animation.FileMovieWriter.cleanup:1:<autosummary>:1"
    ],
    "matplotlib.animation.FileMovieWriter.isAvailable": [
      "doc/api/_as_gen/matplotlib.animation.FileMovieWriter.rst:28:<autosummary>:1"
    ],
    "matplotlib.animation.FileMovieWriter.saving": [
      "doc/api/_as_gen/matplotlib.animation.FileMovieWriter.rst:28:<autosummary>:1"
    ],
    "matplotlib.animation.FuncAnimation.save": [
      "lib/matplotlib/animation.py:docstring of matplotlib.animation.FuncAnimation.new_frame_seq:1:<autosummary>:1"
    ],
    "matplotlib.animation.FuncAnimation.to_html5_video": [
      "lib/matplotlib/animation.py:docstring of matplotlib.animation.FuncAnimation.new_frame_seq:1:<autosummary>:1"
    ],
    "matplotlib.animation.FuncAnimation.to_jshtml": [
      "lib/matplotlib/animation.py:docstring of matplotlib.animation.FuncAnimation.new_frame_seq:1:<autosummary>:1"
    ],
    "matplotlib.animation.HTMLWriter.bin_path": [
      "doc/api/_as_gen/matplotlib.animation.HTMLWriter.rst:28:<autosummary>:1"
    ],
    "matplotlib.animation.HTMLWriter.cleanup": [
      "doc/api/_as_gen/matplotlib.animation.HTMLWriter.rst:28:<autosummary>:1"
    ],
    "matplotlib.animation.HTMLWriter.clear_temp": [
      "lib/matplotlib/animation.py:docstring of matplotlib.animation.HTMLWriter.args_key:1:<autosummary>:1"
    ],
    "matplotlib.animation.HTMLWriter.exec_key": [
      "lib/matplotlib/animation.py:docstring of matplotlib.animation.HTMLWriter.args_key:1:<autosummary>:1"
    ],
    "matplotlib.animation.HTMLWriter.frame_format": [
      "lib/matplotlib/animation.py:docstring of matplotlib.animation.HTMLWriter.args_key:1:<autosummary>:1"
    ],
    "matplotlib.animation.HTMLWriter.frame_size": [
      "lib/matplotlib/animation.py:docstring of matplotlib.animation.HTMLWriter.args_key:1:<autosummary>:1"
    ],
    "matplotlib.animation.HTMLWriter.saving": [
      "doc/api/_as_gen/matplotlib.animation.HTMLWriter.rst:28:<autosummary>:1"
    ],
    "matplotlib.animation.ImageMagickFileWriter.args_key": [
      "lib/matplotlib/animation.py:docstring of matplotlib.animation.ImageMagickFileWriter.supported_formats:1:<autosummary>:1"
    ],
    "matplotlib.animation.ImageMagickFileWriter.bin_path": [
      "doc/api/_as_gen/matplotlib.animation.ImageMagickFileWriter.rst:28:<autosummary>:1"
    ],
    "matplotlib.animation.ImageMagickFileWriter.cleanup": [
      "doc/api/_as_gen/matplotlib.animation.ImageMagickFileWriter.rst:28:<autosummary>:1"
    ],
    "matplotlib.animation.ImageMagickFileWriter.clear_temp": [
      "lib/matplotlib/animation.py:docstring of matplotlib.animation.ImageMagickFileWriter.supported_formats:1:<autosummary>:1"
    ],
    "matplotlib.animation.ImageMagickFileWriter.delay": [
      "lib/matplotlib/animation.py:docstring of matplotlib.animation.ImageMagickFileWriter.supported_formats:1:<autosummary>:1"
    ],
    "matplotlib.animation.ImageMagickFileWriter.exec_key": [
      "lib/matplotlib/animation.py:docstring of matplotlib.animation.ImageMagickFileWriter.supported_formats:1:<autosummary>:1"
    ],
    "matplotlib.animation.ImageMagickFileWriter.finish": [
      "doc/api/_as_gen/matplotlib.animation.ImageMagickFileWriter.rst:28:<autosummary>:1"
    ],
    "matplotlib.animation.ImageMagickFileWriter.frame_format": [
      "lib/matplotlib/animation.py:docstring of matplotlib.animation.ImageMagickFileWriter.supported_formats:1:<autosummary>:1"
    ],
    "matplotlib.animation.ImageMagickFileWriter.frame_size": [
      "lib/matplotlib/animation.py:docstring of matplotlib.animation.ImageMagickFileWriter.supported_formats:1:<autosummary>:1"
    ],
    "matplotlib.animation.ImageMagickFileWriter.grab_frame": [
      "doc/api/_as_gen/matplotlib.animation.ImageMagickFileWriter.rst:28:<autosummary>:1"
    ],
    "matplotlib.animation.ImageMagickFileWriter.isAvailable": [
      "doc/api/_as_gen/matplotlib.animation.ImageMagickFileWriter.rst:28:<autosummary>:1"
    ],
    "matplotlib.animation.ImageMagickFileWriter.output_args": [
      "lib/matplotlib/animation.py:docstring of matplotlib.animation.ImageMagickFileWriter.supported_formats:1:<autosummary>:1"
    ],
    "matplotlib.animation.ImageMagickFileWriter.saving": [
      "doc/api/_as_gen/matplotlib.animation.ImageMagickFileWriter.rst:28:<autosummary>:1"
    ],
    "matplotlib.animation.ImageMagickFileWriter.setup": [
      "doc/api/_as_gen/matplotlib.animation.ImageMagickFileWriter.rst:28:<autosummary>:1"
    ],
    "matplotlib.animation.ImageMagickWriter.args_key": [
      "doc/api/_as_gen/matplotlib.animation.ImageMagickWriter.rst:37:<autosummary>:1"
    ],
    "matplotlib.animation.ImageMagickWriter.bin_path": [
      "doc/api/_as_gen/matplotlib.animation.ImageMagickWriter.rst:28:<autosummary>:1"
    ],
    "matplotlib.animation.ImageMagickWriter.cleanup": [
      "doc/api/_as_gen/matplotlib.animation.ImageMagickWriter.rst:28:<autosummary>:1"
    ],
    "matplotlib.animation.ImageMagickWriter.delay": [
      "doc/api/_as_gen/matplotlib.animation.ImageMagickWriter.rst:37:<autosummary>:1"
    ],
    "matplotlib.animation.ImageMagickWriter.exec_key": [
      "doc/api/_as_gen/matplotlib.animation.ImageMagickWriter.rst:37:<autosummary>:1"
    ],
    "matplotlib.animation.ImageMagickWriter.finish": [
      "doc/api/_as_gen/matplotlib.animation.ImageMagickWriter.rst:28:<autosummary>:1"
    ],
    "matplotlib.animation.ImageMagickWriter.frame_size": [
      "doc/api/_as_gen/matplotlib.animation.ImageMagickWriter.rst:37:<autosummary>:1"
    ],
    "matplotlib.animation.ImageMagickWriter.grab_frame": [
      "doc/api/_as_gen/matplotlib.animation.ImageMagickWriter.rst:28:<autosummary>:1"
    ],
    "matplotlib.animation.ImageMagickWriter.isAvailable": [
      "doc/api/_as_gen/matplotlib.animation.ImageMagickWriter.rst:28:<autosummary>:1"
    ],
    "matplotlib.animation.ImageMagickWriter.output_args": [
      "doc/api/_as_gen/matplotlib.animation.ImageMagickWriter.rst:37:<autosummary>:1"
    ],
    "matplotlib.animation.ImageMagickWriter.saving": [
      "doc/api/_as_gen/matplotlib.animation.ImageMagickWriter.rst:28:<autosummary>:1"
    ],
    "matplotlib.animation.ImageMagickWriter.setup": [
      "doc/api/_as_gen/matplotlib.animation.ImageMagickWriter.rst:28:<autosummary>:1"
    ],
    "matplotlib.animation.MovieWriter.frame_size": [
      "lib/matplotlib/animation.py:docstring of matplotlib.animation.MovieWriter.args_key:1:<autosummary>:1"
    ],
    "matplotlib.animation.MovieWriter.saving": [
      "doc/api/_as_gen/matplotlib.animation.MovieWriter.rst:28:<autosummary>:1"
    ],
    "matplotlib.animation.PillowWriter.frame_size": [
      "lib/matplotlib/animation.py:docstring of matplotlib.animation.PillowWriter.finish:1:<autosummary>:1"
    ],
    "matplotlib.animation.PillowWriter.saving": [
      "doc/api/_as_gen/matplotlib.animation.PillowWriter.rst:26:<autosummary>:1"
    ],
    "matplotlib.animation.TimedAnimation.new_frame_seq": [
      "doc/api/_as_gen/matplotlib.animation.TimedAnimation.rst:21:<autosummary>:1"
    ],
    "matplotlib.animation.TimedAnimation.new_saved_frame_seq": [
      "doc/api/_as_gen/matplotlib.animation.TimedAnimation.rst:21:<autosummary>:1"
    ],
    "matplotlib.animation.TimedAnimation.save": [
      "doc/api/_as_gen/matplotlib.animation.TimedAnimation.rst:21:<autosummary>:1"
    ],
    "matplotlib.animation.TimedAnimation.to_html5_video": [
      "doc/api/_as_gen/matplotlib.animation.TimedAnimation.rst:21:<autosummary>:1"
    ],
    "matplotlib.animation.TimedAnimation.to_jshtml": [
      "doc/api/_as_gen/matplotlib.animation.TimedAnimation.rst:21:<autosummary>:1"
    ],
    "matplotlib.cbook.ls_mapper": [
      "doc/api/prev_api_changes/api_changes_1.5.0.rst:11",
      "doc/api/prev_api_changes/api_changes_1.5.0.rst:8"
    ],
    "matplotlib.colorbar.ColorbarBase.set_clim": [
      "doc/api/prev_api_changes/api_changes_3.1.0.rst:290"
    ],
    "matplotlib.colorbar.ColorbarBase.set_cmap": [
      "doc/api/prev_api_changes/api_changes_3.1.0.rst:290"
    ],
    "matplotlib.colorbar.ColorbarBase.set_norm": [
      "doc/api/prev_api_changes/api_changes_3.1.0.rst:290"
    ],
    "matplotlib.contour.TriContourSet": [
      "lib/matplotlib/pyplot.py:docstring of matplotlib.pyplot.tricontour:57",
      "lib/matplotlib/pyplot.py:docstring of matplotlib.pyplot.tricontourf:57",
      "lib/matplotlib/tri/tricontour.py:docstring of matplotlib.axes.Axes.tricontour:57",
      "lib/matplotlib/tri/tricontour.py:docstring of matplotlib.axes.Axes.tricontourf:57"
    ],
    "matplotlib.dates.rrulewrapper": [
      "lib/matplotlib/dates.py:docstring of matplotlib.dates:103"
    ],
    "matplotlib.docstring.dedent_interpd": [
      "doc/devel/documenting_mpl.rst:663"
    ],
    "matplotlib.patches.Patch.__init__": [
      "doc/devel/documenting_mpl.rst:696"
    ],
    "matplotlib.sphinxext.mathmpl": [
      "doc/users/prev_whats_new/whats_new_3.0.rst:225"
    ],
    "matplotlib.spines.get_window_extent": [
      "lib/matplotlib/axes/_base.py:docstring of matplotlib.axes.Axes.get_window_extent:24"
    ],
    "matplotlib.style.core.STYLE_BLACKLIST": [
      "doc/api/prev_api_changes/api_changes_3.0.0.rst:298",
      "lib/matplotlib/__init__.py:docstring of matplotlib.rc_file:4",
      "lib/matplotlib/__init__.py:docstring of matplotlib.rc_file_defaults:4",
      "lib/matplotlib/__init__.py:docstring of matplotlib.rcdefaults:4",
      "lib/matplotlib/pyplot.py:docstring of matplotlib.pyplot.rcdefaults:4"
    ],
    "matplotlib.testing.compare.calculate_rms": [
      "doc/api/prev_api_changes/api_changes_3.1.0.rst:771"
    ],
    "matplotlib.testing.conftest.mpl_test_settings": [
      "doc/api/prev_api_changes/api_changes_3.1.0.rst:941"
    ],
    "move_canvas": [
      "doc/devel/MEP/MEP23.rst:65"
    ],
    "mpl_toolkits.axes_grid.axes_divider.AxesLocator": [
      "lib/mpl_toolkits/axes_grid1/axes_divider.py:docstring of mpl_toolkits.axes_grid1.axes_divider.HBoxDivider.new_locator:2",
      "lib/mpl_toolkits/axes_grid1/axes_divider.py:docstring of mpl_toolkits.axes_grid1.axes_divider.VBoxDivider.new_locator:2"
    ],
    "mpl_toolkits.axislines.Axes": [
      "lib/mpl_toolkits/axisartist/axis_artist.py:docstring of mpl_toolkits.axisartist.axis_artist:26"
    ],
    "new_figure_manager": [
      "doc/devel/MEP/MEP23.rst:75"
    ],
    "new_figure_manager_given_figure": [
      "doc/devel/MEP/MEP23.rst:78",
      "doc/devel/MEP/MEP23.rst:82"
    ],
    "next_whats_new": [
      "doc/users/next_whats_new/README.rst:6"
    ],
    "numpy.datetime64": [
      "doc/api/prev_api_changes/api_changes_2.1.0.rst:95",
      "doc/faq/howto_faq.rst:18",
      "doc/faq/howto_faq.rst:21",
      "doc/gallery/recipes/common_date_problems.rst:36",
      "doc/gallery/text_labels_and_annotations/date.rst:20",
      "doc/tutorials/text/text_intro.rst:582",
      "doc/users/prev_whats_new/whats_new_2.2.rst:155",
      "lib/matplotlib/dates.py:docstring of matplotlib.dates.date2num:8"
    ],
    "numpy.max": [
      "lib/matplotlib/axes/_axes.py:docstring of matplotlib.axes.Axes.hexbin:125",
      "lib/matplotlib/pyplot.py:docstring of matplotlib.pyplot.hexbin:125"
    ],
    "pillow.Image.save()": [
      "doc/users/prev_whats_new/whats_new_3.1.0.rst:131",
      "doc/users/prev_whats_new/whats_new_3.1.0.rst:135"
    ],
    "plot": [
      "lib/matplotlib/sphinxext/plot_directive.py:docstring of matplotlib.sphinxext.plot_directive:4"
    ],
    "plot_include_source": [
      "lib/matplotlib/sphinxext/plot_directive.py:docstring of matplotlib.sphinxext.plot_directive:52"
    ],
    "print_xyz": [
      "lib/matplotlib/backends/backend_template.py:docstring of matplotlib.backends.backend_template:22"
    ],
    "pyplot.set_loglevel": [
      "doc/users/prev_whats_new/whats_new_3.1.0.rst:377"
    ],
    "remove_canvas": [
      "doc/devel/MEP/MEP23.rst:63"
    ],
    "rrulewrapper": [
      "lib/matplotlib/dates.py:docstring of matplotlib.dates:103"
    ],
    "scipy.stats.norm.pdf": [
      "doc/api/prev_api_changes/api_changes_3.1.0.rst:565",
      "doc/api/prev_api_changes/api_changes_3.1.0.rst:651"
    ],
    "self.codes": [
      "lib/matplotlib/path.py:docstring of matplotlib.path.Path.codes:2"
    ],
    "self.vertices": [
      "lib/matplotlib/path.py:docstring of matplotlib.path.Path.codes:2"
    ],
    "set_active_canvas": [
      "doc/devel/MEP/MEP23.rst:70"
    ],
    "set_canvas_title": [
      "doc/devel/MEP/MEP23.rst:66"
    ],
    "set_size": [
      "doc/users/prev_whats_new/whats_new_1.4.rst:223"
    ],
    "set_xbound": [
      "lib/mpl_toolkits/mplot3d/axes3d.py:docstring of mpl_toolkits.mplot3d.axes3d.Axes3D.get_xlim3d:22"
    ],
    "set_ybound": [
      "lib/mpl_toolkits/mplot3d/axes3d.py:docstring of mpl_toolkits.mplot3d.axes3d.Axes3D.get_ylim3d:22"
    ],
    "shadow_rgbFace": [
      "lib/matplotlib/patheffects.py:docstring of matplotlib.patheffects.SimpleLineShadow:39",
      "lib/matplotlib/patheffects.py:docstring of matplotlib.patheffects.SimplePatchShadow:38",
      "lib/matplotlib/patheffects.py:docstring of matplotlib.patheffects.withSimplePatchShadow:47"
    ],
    "show": [
      "doc/devel/MEP/MEP23.rst:70"
    ],
    "size_vertical": [
      "lib/mpl_toolkits/axes_grid1/anchored_artists.py:docstring of mpl_toolkits.axes_grid1.anchored_artists.AnchoredSizeBar:59"
    ],
    "sphinx-autogen": [
      "doc/devel/MEP/MEP10.rst:162"
    ],
    "sphinx-quickstart": [
      "doc/devel/MEP/MEP10.rst:170"
    ],
    "streamplot.Grid": [
      "doc/api/prev_api_changes/api_changes_3.1.0.rst:479"
    ],
    "style.available": [
      "lib/matplotlib/style/__init__.py:docstring of matplotlib.style.context:12",
      "lib/matplotlib/style/__init__.py:docstring of matplotlib.style.use:19"
    ],
    "tight_bbox.adjust_bbox": [
      "doc/api/prev_api_changes/api_changes_1.4.x.rst:152"
    ],
    "tight_bbox.process_figure_for_rasterizing": [
      "doc/api/prev_api_changes/api_changes_1.4.x.rst:152"
    ],
    "to_html5_video": [
      "doc/users/prev_whats_new/whats_new_1.5.rst:728"
    ],
    "toggled": [
      "lib/matplotlib/backend_tools.py:docstring of matplotlib.backend_tools.AxisScaleBase.disable:4",
      "lib/matplotlib/backend_tools.py:docstring of matplotlib.backend_tools.AxisScaleBase.enable:4",
      "lib/matplotlib/backend_tools.py:docstring of matplotlib.backend_tools.AxisScaleBase.trigger:2",
      "lib/matplotlib/backend_tools.py:docstring of matplotlib.backend_tools.ToolFullScreen.disable:4",
      "lib/matplotlib/backend_tools.py:docstring of matplotlib.backend_tools.ToolFullScreen.enable:4",
      "lib/matplotlib/backend_tools.py:docstring of matplotlib.backend_tools.ZoomPanBase.trigger:2"
    ],
    "tool_added_event": [
      "doc/devel/MEP/MEP22.rst:171"
    ],
    "tool_removed_event": [
      "lib/matplotlib/backend_bases.py:docstring of matplotlib.backend_bases.ToolContainerBase.remove_toolitem:6"
    ],
    "toolbar": [
      "doc/users/prev_whats_new/whats_new_1.5.rst:615"
    ],
    "trigger": [
      "doc/users/prev_whats_new/whats_new_1.5.rst:615",
      "lib/matplotlib/backend_tools.py:docstring of matplotlib.backend_tools.ToolFullScreen.disable:4",
      "lib/matplotlib/backend_tools.py:docstring of matplotlib.backend_tools.ToolFullScreen.enable:4"
    ],
    "w_pad": [
      "lib/matplotlib/figure.py:docstring of matplotlib.figure.Figure.set_constrained_layout:5"
    ],
    "warn": [
      "doc/devel/contributing.rst:517"
    ],
    "whats_new.rst": [
      "doc/users/next_whats_new/README.rst:6"
    ],
    "xaxis_inverted": [
      "lib/mpl_toolkits/mplot3d/axes3d.py:docstring of mpl_toolkits.mplot3d.axes3d.Axes3D.get_xlim3d:24"
    ],
    "yaxis_inverted": [
      "lib/mpl_toolkits/mplot3d/axes3d.py:docstring of mpl_toolkits.mplot3d.axes3d.Axes3D.get_ylim3d:24"
    ]
  }
}
